compose_rename.py
compose_rename-0.4.0.dist-info/METADATA
compose_rename-0.4.0.dist-info/WHEEL
compose_rename-0.4.0.dist-info/entry_points.txt
compose_rename-0.4.0.dist-info/RECORD
