Metadata-Version: 2.4
Name: compose-rename
Version: 0.4.0
Summary: Rename a Docker Compose project by migrating volumes to a new project prefix.
Project-URL: Homepage, https://github.com/jonasjancarik/compose-rename
Author: Your Name
License: MIT
Requires-Python: >=3.10
Requires-Dist: pyyaml>=6.0
